unextexams/__init__.py
unextexams/unextexams.py
unextexams-0.3.1.4.dist-info/LICENSE
unextexams-0.3.1.4.dist-info/METADATA
unextexams-0.3.1.4.dist-info/WHEEL
unextexams-0.3.1.4.dist-info/top_level.txt
unextexams-0.3.1.4.dist-info/RECORD
